audipart/__init__.py
audipart/__main__.py
audipart-0.0.4.dist-info/METADATA
audipart-0.0.4.dist-info/WHEEL
audipart-0.0.4.dist-info/RECORD
