Metadata-Version: 2.4
Name: audipart
Version: 0.0.4
Summary: Extract and separate audio signals by pitch from `.mp3` or `.wav` files.
Project-URL: Homepage, https://github.com/hepheir/audio-pitch-separation
Project-URL: Issues, https://github.com/hepheir/audio-pitch-separation/issues
Author-email: Hepheir <hepheir@gmail.com>
License-Expression: MIT
Classifier: Operating System :: OS Independent
Classifier: Programming Language :: Python :: 3
Requires-Python: >=3.9
Requires-Dist: librosa
Requires-Dist: matplotlib
Requires-Dist: numpy
Requires-Dist: pydub
Requires-Dist: pyqt5
Requires-Dist: soundfile
